DaiNiRumenQianduanGongcheng/README.md
DaiNiRumenQianduanGongcheng/__init__.py
DaiNiRumenQianduanGongcheng/__main__.py
DaiNiRumenQianduanGongcheng/file.epub
DaiNiRumenQianduanGongcheng/index.html
DaiNiRumenQianduanGongcheng/css/__init__.py
DaiNiRumenQianduanGongcheng/css/annotations.css
DaiNiRumenQianduanGongcheng/css/main.css
DaiNiRumenQianduanGongcheng/css/normalize.css
DaiNiRumenQianduanGongcheng/css/popup.css
DaiNiRumenQianduanGongcheng/font/__init__.py
DaiNiRumenQianduanGongcheng/font/fontello.eot
DaiNiRumenQianduanGongcheng/font/fontello.svg
DaiNiRumenQianduanGongcheng/font/fontello.ttf
DaiNiRumenQianduanGongcheng/font/fontello.woff
DaiNiRumenQianduanGongcheng/img/__init__.py
DaiNiRumenQianduanGongcheng/img/annotator-glyph-sprite.png
DaiNiRumenQianduanGongcheng/img/annotator-icon-sprite.png
DaiNiRumenQianduanGongcheng/img/apple-touch-icon.png
DaiNiRumenQianduanGongcheng/img/cancelfullscreen.png
DaiNiRumenQianduanGongcheng/img/close.png
DaiNiRumenQianduanGongcheng/img/fullscreen.png
DaiNiRumenQianduanGongcheng/img/loader.gif
DaiNiRumenQianduanGongcheng/img/menu-icon.png
DaiNiRumenQianduanGongcheng/img/save.png
DaiNiRumenQianduanGongcheng/img/saved.png
DaiNiRumenQianduanGongcheng/img/settings-s.png
DaiNiRumenQianduanGongcheng/img/settings.png
DaiNiRumenQianduanGongcheng/img/star.png
DaiNiRumenQianduanGongcheng/js/__init__.py
DaiNiRumenQianduanGongcheng/js/epub.js
DaiNiRumenQianduanGongcheng/js/epub.min.js
DaiNiRumenQianduanGongcheng/js/epub.min.map
DaiNiRumenQianduanGongcheng/js/hooks.min.js
DaiNiRumenQianduanGongcheng/js/hooks.min.map
DaiNiRumenQianduanGongcheng/js/reader.js
DaiNiRumenQianduanGongcheng/js/reader.js.map
DaiNiRumenQianduanGongcheng/js/reader.min.js
DaiNiRumenQianduanGongcheng/js/reader.min.map
DaiNiRumenQianduanGongcheng/js/hooks/__init__.py
DaiNiRumenQianduanGongcheng/js/hooks/extensions/__init__.py
DaiNiRumenQianduanGongcheng/js/hooks/extensions/highlight.js
DaiNiRumenQianduanGongcheng/js/libs/__init__.py
dai_ni_rumen_qianduan_gongcheng-2024.3.5.0.dist-info/METADATA
dai_ni_rumen_qianduan_gongcheng-2024.3.5.0.dist-info/WHEEL
dai_ni_rumen_qianduan_gongcheng-2024.3.5.0.dist-info/entry_points.txt
dai_ni_rumen_qianduan_gongcheng-2024.3.5.0.dist-info/top_level.txt
dai_ni_rumen_qianduan_gongcheng-2024.3.5.0.dist-info/RECORD
